xsdata_attrs/__init__.py
xsdata_attrs/bindings.py
xsdata_attrs/compat.py
xsdata_attrs/generator.py
xsdata_attrs/py.typed
xsdata_attrs/hooks/__init__.py
xsdata_attrs/hooks/class_type.py
xsdata_attrs/hooks/cli.py
xsdata_attrs-24.5.dist-info/LICENSE
xsdata_attrs-24.5.dist-info/METADATA
xsdata_attrs-24.5.dist-info/WHEEL
xsdata_attrs-24.5.dist-info/entry_points.txt
xsdata_attrs-24.5.dist-info/top_level.txt
xsdata_attrs-24.5.dist-info/RECORD
