Metadata-Version: 2.1
Name: xsdata_attrs
Version: 24.5
Summary: xsdata attrs plugin
Author-email: Christodoulos Tsoulloftas <chris@komposta.net>
License: MIT
Project-URL: Homepage, https://github.com/tefra/xsdata-attrs
Project-URL: Source, https://github.com/tefra/xsdata-attrs
Project-URL: Documentation, https://xsdata-attrs.readthedocs.io/
Project-URL: Changelog, https://xsdata-attrs.readthedocs.io/en/latest/changelog/
Keywords: xsd,wsdl,schema,dtd,binding,xml,json,dataclasses,generator,cli,attrs
Classifier: Intended Audience :: Developers
Classifier: License :: OSI Approved :: MIT License
Classifier: Operating System :: OS Independent
Classifier: Programming Language :: Python
Classifier: Programming Language :: Python :: 3
Classifier: Programming Language :: Python :: 3 :: Only
Classifier: Programming Language :: Python :: 3.8
Classifier: Programming Language :: Python :: 3.9
Classifier: Programming Language :: Python :: 3.10
Classifier: Programming Language :: Python :: 3.11
Classifier: Programming Language :: Python :: 3.12
Classifier: Programming Language :: Python :: Implementation :: CPython
Classifier: Programming Language :: Python :: Implementation :: PyPy
Classifier: Topic :: Software Development :: Code Generators
Classifier: Topic :: Text Processing :: Markup :: XML
Requires-Python: >=3.8
License-File: LICENSE
Requires-Dist: attrs >=19.2.0
Requires-Dist: xsdata >=24.5
Provides-Extra: cli
Requires-Dist: xsdata[cli] >=23.5 ; extra == 'cli'
Provides-Extra: docs
Requires-Dist: mkdocs ; extra == 'docs'
Requires-Dist: mkdocs-gen-files ; extra == 'docs'
Requires-Dist: mkdocs-literate-nav ; extra == 'docs'
Requires-Dist: mkdocs-material ; extra == 'docs'
Requires-Dist: mkdocs-minify-plugin ; extra == 'docs'
Requires-Dist: mkdocstrings[python] ; extra == 'docs'
Requires-Dist: markdown-exec[ansi] ; extra == 'docs'
Requires-Dist: pymdownx-superfence-filter-lines ; extra == 'docs'
Provides-Extra: lxml
Requires-Dist: lxml >=4.5.0 ; extra == 'lxml'
Provides-Extra: soap
Requires-Dist: requests ; extra == 'soap'
Provides-Extra: test
Requires-Dist: codecov ; extra == 'test'
Requires-Dist: lxml ; extra == 'test'
Requires-Dist: pre-commit ; extra == 'test'
Requires-Dist: pytest ; extra == 'test'
Requires-Dist: pytest-cov ; extra == 'test'
